wasscli/__init__.py
wasscli/__main__.py
wasscli/wasscli.py
wasscli-0.1.11.dist-info/METADATA
wasscli-0.1.11.dist-info/WHEEL
wasscli-0.1.11.dist-info/entry_points.txt
wasscli-0.1.11.dist-info/top_level.txt
wasscli-0.1.11.dist-info/RECORD
