Metadata-Version: 2.4
Name: wasscli
Version: 0.1.11
Summary: WASS command line interface
Author: Filippo Bergamasco
Author-email: filippo.bergamasco@unive.it
License: GPL3
Project-URL: homepage, https://sites.google.com/unive.it/wass
Project-URL: repository, https://github.com/fbergama/wass/tree/master/cli
Keywords: WASS,3D,Interpolation
Classifier: Programming Language :: Python :: 3
Classifier: Development Status :: 4 - Beta
Requires-Python: >=3.9
Requires-Dist: tqdm>=4.42.0
Requires-Dist: InquirerPy
Requires-Dist: colorama
Requires-Dist: numpy
